todo2notion/__init__.py
todo2notion/__main__.py
todo2notion/config.py
todo2notion/notion_helper.py
todo2notion/notion_renderer.py
todo2notion/todo.py
todo2notion/update_heatmap.py
todo2notion/utils.py
todo2notion-0.1.8.dist-info/METADATA
todo2notion-0.1.8.dist-info/WHEEL
todo2notion-0.1.8.dist-info/entry_points.txt
todo2notion-0.1.8.dist-info/top_level.txt
todo2notion-0.1.8.dist-info/RECORD
